README.md
setup.py
apiage/__init__.py
apiage.egg-info/PKG-INFO
apiage.egg-info/SOURCES.txt
apiage.egg-info/dependency_links.txt
apiage.egg-info/not-zip-safe
apiage.egg-info/requires.txt
apiage.egg-info/top_level.txt