Metadata-Version: 2.1
Name: apiage
Version: 0.1.0
Summary: Gets pages from API.
Home-page: https://gitlab.com/mindey/apiage
Author: Mindey
Author-email: mindey@qq.com
License: UNDEFINED
Platform: UNKNOWN
Provides-Extra: test
